mlgen/__init__.py
mlgen/__main__.py
mlgen/mlgen_code.py
mlgen/mlm_templates/ann_keras.mlm
mlgen/mlm_templates/ann_tensorflow2.mlm
mlgen/mlm_templates/cnn_keras.mlm
mlgen/mlm_templates/cnn_tensorflow2.mlm
mlgen/mlm_templates/lstm_keras.mlm
mlgen/mlm_templates/lstm_tensorflow2.mlm
mlgen/template/linreg.txt
mlgen/template/python3_jup.ipynb
mlgen-1.0.5.dist-info/METADATA
mlgen-1.0.5.dist-info/WHEEL
mlgen-1.0.5.dist-info/entry_points.txt
mlgen-1.0.5.dist-info/top_level.txt
mlgen-1.0.5.dist-info/RECORD
