Metadata-Version: 2.1
Name: mlgen
Version: 1.0.5
Summary: MLGen is a tool which helps you to generate machine learning code with ease.
Home-page: https://github.com/NebutechOpenSource/MLGen
Author: Nebutech
Author-email: mukundh.bhushan@nebutech.in
License: MIT
Platform: UNKNOWN
Classifier: Development Status :: 3 - Alpha
Classifier: Intended Audience :: Developers
Classifier: Topic :: Software Development :: Build Tools
Classifier: License :: OSI Approved :: MIT License
Classifier: Programming Language :: Python :: 3
Classifier: Programming Language :: Python :: 3.4
Classifier: Programming Language :: Python :: 3.5
Classifier: Programming Language :: Python :: 3.6
Classifier: Programming Language :: Python :: 3.7
Requires-Dist: pyyaml
